KalaNeroNetwork/KalaNeroNetwork.py
KalaNeroNetwork/__init__.py
Kala_NuroNetwork-0.1.0.dist-info/METADATA
Kala_NuroNetwork-0.1.0.dist-info/WHEEL
Kala_NuroNetwork-0.1.0.dist-info/top_level.txt
Kala_NuroNetwork-0.1.0.dist-info/RECORD
