Metadata-Version: 2.1
Name: Kala_NuroNetwork
Version: 0.1.0
Summary: A hybrid quantum-classical neural network framework using Kala_Quantum and Kala_Torch
Home-page: https://github.com/Kalasaikamesh944/Kala_NuroNetwork
Author: N V R K SAI KAMESH YADAVALLI
Author-email: saikamesh.y@gmail.com
Classifier: Programming Language :: Python :: 3
Classifier: License :: OSI Approved :: MIT License
Classifier: Operating System :: OS Independent
Requires-Python: >=3.8
Requires-Dist: torch
Requires-Dist: Kala-Quantum-185
Requires-Dist: Kala_Torch
